[
  {
    "ea": "0x14011de10",
    "module": "USER32",
    "name": "IsRectEmpty",
    "ordinal": 0
  },
  {
    "ea": "0x14011de18",
    "module": "USER32",
    "name": "PtInRect",
    "ordinal": 0
  },
  {
    "ea": "0x14011de20",
    "module": "USER32",
    "name": "GetClassInfoW",
    "ordinal": 0
  },
  {
    "ea": "0x14011de28",
    "module": "USER32",
    "name": "DefDlgProcW",
    "ordinal": 0
  },
  {
    "ea": "0x14011de30",
    "module": "USER32",
    "name": "LoadStringW",
    "ordinal": 0
  },
  {
    "ea": "0x14011de38",
    "module": "USER32",
    "name": "MessageBoxW",
    "ordinal": 0
  },
  {
    "ea": "0x14011de40",
    "module": "USER32",
    "name": "GetMenuItemCount",
    "ordinal": 0
  },
  {
    "ea": "0x14011de48",
    "module": "USER32",
    "name": "InsertMenuItemW",
    "ordinal": 0
  },
  {
    "ea": "0x14011de50",
    "module": "USER32",
    "name": "AllowSetForegroundWindow",
    "ordinal": 0
  },
  {
    "ea": "0x14011de58",
    "module": "USER32",
    "name": "CreateDialogParamW",
    "ordinal": 0
  },
  {
    "ea": "0x14011de60",
    "module": "USER32",
    "name": "DialogBoxParamW",
    "ordinal": 0
  },
  {
    "ea": "0x14011de68",
    "module": "USER32",
    "name": "LoadAcceleratorsW",
    "ordinal": 0
  },
  {
    "ea": "0x14011de70",
    "module": "USER32",
    "name": "MsgWaitForMultipleObjectsEx",
    "ordinal": 0
  },
  {
    "ea": "0x14011de78",
    "module": "USER32",
    "name": "PeekMessageW",
    "ordinal": 0
  },
  {
    "ea": "0x14011de80",
    "module": "USER32",
    "name": "MsgWaitForMultipleObjects",
    "ordinal": 0
  },
  {
    "ea": "0x14011de88",
    "module": "USER32",
    "name": "MonitorFromWindow",
    "ordinal": 0
  },
  {
    "ea": "0x14011de90",
    "module": "USER32",
    "name": "UnregisterClassA",
    "ordinal": 0
  },
  {
    "ea": "0x14011de98",
    "module": "USER32",
    "name": "RegisterClassW",
    "ordinal": 0
  },
  {
    "ea": "0x14011dea0",
    "module": "USER32",
    "name": "SetProcessDPIAware",
    "ordinal": 0
  },
  {
    "ea": "0x14011dea8",
    "module": "USER32",
    "name": "ScrollWindow",
    "ordinal": 0
  },
  {
    "ea": "0x14011deb0",
    "module": "USER32",
    "name": "GetScrollInfo",
    "ordinal": 0
  },
  {
    "ea": "0x14011deb8",
    "module": "USER32",
    "name": "GetDpiForWindow",
    "ordinal": 0
  },
  {
    "ea": "0x14011dec0",
    "module": "USER32",
    "name": "SetScrollInfo",
    "ordinal": 0
  },
  {
    "ea": "0x14011dec8",
    "module": "USER32",
    "name": "CharNextW",
    "ordinal": 0
  },
  {
    "ea": "0x14011ded0",
    "module": "USER32",
    "name": "GetKeyboardLayout",
    "ordinal": 0
  },
  {
    "ea": "0x14011ded8",
    "module": "USER32",
    "name": "CharLowerW",
    "ordinal": 0
  },
  {
    "ea": "0x14011dee0",
    "module": "USER32",
    "name": "EnumDisplayDevicesW",
    "ordinal": 0
  },
  {
    "ea": "0x14011dee8",
    "module": "USER32",
    "name": "CheckRadioButton",
    "ordinal": 0
  },
  {
    "ea": "0x14011def0",
    "module": "USER32",
    "name": "DrawIconEx",
    "ordinal": 0
  },
  {
    "ea": "0x14011def8",
    "module": "USER32",
    "name": "MapDialogRect",
    "ordinal": 0
  },
  {
    "ea": "0x14011df00",
    "module": "USER32",
    "name": "ScreenToClient",
    "ordinal": 0
  },
  {
    "ea": "0x14011df08",
    "module": "USER32",
    "name": "SubtractRect",
    "ordinal": 0
  },
  {
    "ea": "0x14011df10",
    "module": "USER32",
    "name": "GetMonitorInfoW",
    "ordinal": 0
  },
  {
    "ea": "0x14011df18",
    "module": "USER32",
    "name": "GetWindowDC",
    "ordinal": 0
  },
  {
    "ea": "0x14011df20",
    "module": "USER32",
    "name": "DrawFocusRect",
    "ordinal": 0
  },
  {
    "ea": "0x14011df28",
    "module": "USER32",
    "name": "GetFocus",
    "ordinal": 0
  },
  {
    "ea": "0x14011df30",
    "module": "USER32",
    "name": "DrawTextW",
    "ordinal": 0
  },
  {
    "ea": "0x14011df38",
    "module": "USER32",
    "name": "EnumDisplayMonitors",
    "ordinal": 0
  },
  {
    "ea": "0x14011df40",
    "module": "USER32",
    "name": "IsDlgButtonChecked",
    "ordinal": 0
  },
  {
    "ea": "0x14011df48",
    "module": "USER32",
    "name": "GetDlgItemTextW",
    "ordinal": 0
  },
  {
    "ea": "0x14011df50",
    "module": "USER32",
    "name": "CreateDialogIndirectParamW",
    "ordinal": 0
  },
  {
    "ea": "0x14011df58",
    "module": "USER32",
    "name": "EndPaint",
    "ordinal": 0
  },
  {
    "ea": "0x14011df60",
    "module": "USER32",
    "name": "DrawIcon",
    "ordinal": 0
  },
  {
    "ea": "0x14011df68",
    "module": "USER32",
    "name": "BeginPaint",
    "ordinal": 0
  },
  {
    "ea": "0x14011df70",
    "module": "USER32",
    "name": "SendDlgItemMessageW",
    "ordinal": 0
  },
  {
    "ea": "0x14011df78",
    "module": "USER32",
    "name": "GetAncestor",
    "ordinal": 0
  },
  {
    "ea": "0x14011df80",
    "module": "USER32",
    "name": "MapWindowPoints",
    "ordinal": 0
  },
  {
    "ea": "0x14011df88",
    "module": "USER32",
    "name": "ReleaseDC",
    "ordinal": 0
  },
  {
    "ea": "0x14011df90",
    "module": "USER32",
    "name": "GetDC",
    "ordinal": 0
  },
  {
    "ea": "0x14011df98",
    "module": "USER32",
    "name": "IsWindowEnabled",
    "ordinal": 0
  },
  {
    "ea": "0x14011dfa0",
    "module": "USER32",
    "name": "FlashWindowEx",
    "ordinal": 0
  },
  {
    "ea": "0x14011dfa8",
    "module": "USER32",
    "name": "SetTimer",
    "ordinal": 0
  },
  {
    "ea": "0x14011dfb0",
    "module": "USER32",
    "name": "GetMenu",
    "ordinal": 0
  },
  {
    "ea": "0x14011dfb8",
    "module": "USER32",
    "name": "KillTimer",
    "ordinal": 0
  },
  {
    "ea": "0x14011dfc0",
    "module": "USER32",
    "name": "ShowWindowAsync",
    "ordinal": 0
  },
  {
    "ea": "0x14011dfc8",
    "module": "USER32",
    "name": "GetWindowTextW",
    "ordinal": 0
  },
  {
    "ea": "0x14011dfd0",
    "module": "USER32",
    "name": "GetClassNameW",
    "ordinal": 0
  },
  {
    "ea": "0x14011dfd8",
    "module": "USER32",
    "name": "GetWindow",
    "ordinal": 0
  },
  {
    "ea": "0x14011dfe0",
    "module": "USER32",
    "name": "RedrawWindow",
    "ordinal": 0
  },
  {
    "ea": "0x14011dfe8",
    "module": "USER32",
    "name": "AdjustWindowRectEx",
    "ordinal": 0
  },
  {
    "ea": "0x14011dff0",
    "module": "USER32",
    "name": "EnumDisplaySettingsExW",
    "ordinal": 0
  },
  {
    "ea": "0x14011dff8",
    "module": "USER32",
    "name": "FillRect",
    "ordinal": 0
  },
  {
    "ea": "0x14011e000",
    "module": "USER32",
    "name": "GetCursorPos",
    "ordinal": 0
  },
  {
    "ea": "0x14011e008",
    "module": "USER32",
    "name": "GetTitleBarInfo",
    "ordinal": 0
  },
  {
    "ea": "0x14011e010",
    "module": "USER32",
    "name": "SendInput",
    "ordinal": 0
  },
  {
    "ea": "0x14011e018",
    "module": "USER32",
    "name": "EqualRect",
    "ordinal": 0
  },
  {
    "ea": "0x14011e020",
    "module": "USER32",
    "name": "EnableWindow",
    "ordinal": 0
  },
  {
    "ea": "0x14011e028",
    "module": "USER32",
    "name": "IsWindowVisible",
    "ordinal": 0
  },
  {
    "ea": "0x14011e030",
    "module": "USER32",
    "name": "SetWindowRgn",
    "ordinal": 0
  },
  {
    "ea": "0x14011e038",
    "module": "USER32",
    "name": "SetWindowLongW",
    "ordinal": 0
  },
  {
    "ea": "0x14011e040",
    "module": "USER32",
    "name": "LockWindowUpdate",
    "ordinal": 0
  },
  {
    "ea": "0x14011e048",
    "module": "USER32",
    "name": "UpdateWindow",
    "ordinal": 0
  },
  {
    "ea": "0x14011e050",
    "module": "USER32",
    "name": "InvalidateRect",
    "ordinal": 0
  },
  {
    "ea": "0x14011e058",
    "module": "USER32",
    "name": "SetWindowTextW",
    "ordinal": 0
  },
  {
    "ea": "0x14011e060",
    "module": "USER32",
    "name": "MoveWindow",
    "ordinal": 0
  },
  {
    "ea": "0x14011e068",
    "module": "USER32",
    "name": "EnableMenuItem",
    "ordinal": 0
  },
  {
    "ea": "0x14011e070",
    "module": "USER32",
    "name": "CheckMenuItem",
    "ordinal": 0
  },
  {
    "ea": "0x14011e078",
    "module": "USER32",
    "name": "SetMenuItemInfoW",
    "ordinal": 0
  },
  {
    "ea": "0x14011e080",
    "module": "USER32",
    "name": "UnregisterClassW",
    "ordinal": 0
  },
  {
    "ea": "0x14011e088",
    "module": "USER32",
    "name": "GetClassInfoExW",
    "ordinal": 0
  },
  {
    "ea": "0x14011e090",
    "module": "USER32",
    "name": "ShowWindow",
    "ordinal": 0
  },
  {
    "ea": "0x14011e098",
    "module": "USER32",
    "name": "GetClientRect",
    "ordinal": 0
  },
  {
    "ea": "0x14011e0a0",
    "module": "USER32",
    "name": "SetWindowPlacement",
    "ordinal": 0
  },
  {
    "ea": "0x14011e0a8",
    "module": "USER32",
    "name": "GetWindowLongW",
    "ordinal": 0
  },
  {
    "ea": "0x14011e0b0",
    "module": "USER32",
    "name": "IsZoomed",
    "ordinal": 0
  },
  {
    "ea": "0x14011e0b8",
    "module": "USER32",
    "name": "LoadCursorW",
    "ordinal": 0
  },
  {
    "ea": "0x14011e0c0",
    "module": "USER32",
    "name": "SetCursor",
    "ordinal": 0
  },
  {
    "ea": "0x14011e0c8",
    "module": "USER32",
    "name": "ModifyMenuW",
    "ordinal": 0
  },
  {
    "ea": "0x14011e0d0",
    "module": "USER32",
    "name": "GetSystemMenu",
    "ordinal": 0
  },
  {
    "ea": "0x14011e0d8",
    "module": "USER32",
    "name": "GetMenuItemInfoW",
    "ordinal": 0
  },
  {
    "ea": "0x14011e0e0",
    "module": "USER32",
    "name": "DeleteMenu",
    "ordinal": 0
  },
  {
    "ea": "0x14011e0e8",
    "module": "USER32",
    "name": "CreateMenu",
    "ordinal": 0
  },
  {
    "ea": "0x14011e0f0",
    "module": "USER32",
    "name": "InsertMenuW",
    "ordinal": 0
  },
  {
    "ea": "0x14011e0f8",
    "module": "USER32",
    "name": "AppendMenuW",
    "ordinal": 0
  },
  {
    "ea": "0x14011e100",
    "module": "USER32",
    "name": "PostQuitMessage",
    "ordinal": 0
  },
  {
    "ea": "0x14011e108",
    "module": "USER32",
    "name": "IsWindow",
    "ordinal": 0
  },
  {
    "ea": "0x14011e110",
    "module": "USER32",
    "name": "DestroyIcon",
    "ordinal": 0
  },
  {
    "ea": "0x14011e118",
    "module": "USER32",
    "name": "LoadImageW",
    "ordinal": 0
  },
  {
    "ea": "0x14011e120",
    "module": "USER32",
    "name": "RegisterWindowMessageW",
    "ordinal": 0
  },
  {
    "ea": "0x14011e128",
    "module": "USER32",
    "name": "SetRect",
    "ordinal": 0
  },
  {
    "ea": "0x14011e130",
    "module": "USER32",
    "name": "CopyRect",
    "ordinal": 0
  },
  {
    "ea": "0x14011e138",
    "module": "USER32",
    "name": "GetDesktopWindow",
    "ordinal": 0
  },
  {
    "ea": "0x14011e140",
    "module": "USER32",
    "name": "SetWindowPos",
    "ordinal": 0
  },
  {
    "ea": "0x14011e148",
    "module": "USER32",
    "name": "IntersectRect",
    "ordinal": 0
  },
  {
    "ea": "0x14011e150",
    "module": "USER32",
    "name": "OffsetRect",
    "ordinal": 0
  },
  {
    "ea": "0x14011e158",
    "module": "USER32",
    "name": "SystemParametersInfoA",
    "ordinal": 0
  },
  {
    "ea": "0x14011e160",
    "module": "USER32",
    "name": "GetWindowRect",
    "ordinal": 0
  },
  {
    "ea": "0x14011e168",
    "module": "USER32",
    "name": "GetWindowPlacement",
    "ordinal": 0
  },
  {
    "ea": "0x14011e170",
    "module": "USER32",
    "name": "IsIconic",
    "ordinal": 0
  },
  {
    "ea": "0x14011e178",
    "module": "USER32",
    "name": "GetSystemMetrics",
    "ordinal": 0
  },
  {
    "ea": "0x14011e180",
    "module": "USER32",
    "name": "LoadIconW",
    "ordinal": 0
  },
  {
    "ea": "0x14011e188",
    "module": "USER32",
    "name": "SetForegroundWindow",
    "ordinal": 0
  },
  {
    "ea": "0x14011e190",
    "module": "USER32",
    "name": "DefWindowProcW",
    "ordinal": 0
  },
  {
    "ea": "0x14011e198",
    "module": "USER32",
    "name": "GetWindowLongPtrW",
    "ordinal": 0
  },
  {
    "ea": "0x14011e1a0",
    "module": "USER32",
    "name": "SetWindowLongPtrW",
    "ordinal": 0
  },
  {
    "ea": "0x14011e1a8",
    "module": "USER32",
    "name": "RegisterClassExW",
    "ordinal": 0
  },
  {
    "ea": "0x14011e1b0",
    "module": "USER32",
    "name": "IsChild",
    "ordinal": 0
  },
  {
    "ea": "0x14011e1b8",
    "module": "USER32",
    "name": "CreateWindowExW",
    "ordinal": 0
  },
  {
    "ea": "0x14011e1c0",
    "module": "USER32",
    "name": "DestroyWindow",
    "ordinal": 0
  },
  {
    "ea": "0x14011e1c8",
    "module": "USER32",
    "name": "GetDlgItem",
    "ordinal": 0
  },
  {
    "ea": "0x14011e1d0",
    "module": "USER32",
    "name": "SetFocus",
    "ordinal": 0
  },
  {
    "ea": "0x14011e1d8",
    "module": "USER32",
    "name": "SetDlgItemTextW",
    "ordinal": 0
  },
  {
    "ea": "0x14011e1e0",
    "module": "USER32",
    "name": "EndDialog",
    "ordinal": 0
  },
  {
    "ea": "0x14011e1e8",
    "module": "USER32",
    "name": "CheckDlgButton",
    "ordinal": 0
  },
  {
    "ea": "0x14011e1f0",
    "module": "USER32",
    "name": "SendMessageW",
    "ordinal": 0
  },
  {
    "ea": "0x14011e1f8",
    "module": "USER32",
    "name": "PostMessageW",
    "ordinal": 0
  },
  {
    "ea": "0x14011e200",
    "module": "USER32",
    "name": "PostThreadMessageW",
    "ordinal": 0
  },
  {
    "ea": "0x14011e208",
    "module": "USER32",
    "name": "IsDialogMessageW",
    "ordinal": 0
  },
  {
    "ea": "0x14011e210",
    "module": "USER32",
    "name": "TranslateAcceleratorW",
    "ordinal": 0
  },
  {
    "ea": "0x14011e218",
    "module": "USER32",
    "name": "DispatchMessageW",
    "ordinal": 0
  },
  {
    "ea": "0x14011e220",
    "module": "USER32",
    "name": "TranslateMessage",
    "ordinal": 0
  },
  {
    "ea": "0x14011e228",
    "module": "USER32",
    "name": "GetMessageW",
    "ordinal": 0
  },
  {
    "ea": "0x14011e230",
    "module": "USER32",
    "name": "CharUpperW",
    "ordinal": 0
  },
  {
    "ea": "0x14011e238",
    "module": "USER32",
    "name": "SystemParametersInfoW",
    "ordinal": 0
  },
  {
    "ea": "0x14011e2e0",
    "module": "msvcrt",
    "name": "memcmp",
    "ordinal": 0
  },
  {
    "ea": "0x14011e2e8",
    "module": "msvcrt",
    "name": "ceil",
    "ordinal": 0
  },
  {
    "ea": "0x14011e2f0",
    "module": "msvcrt",
    "name": "?terminate@@YAXXZ",
    "ordinal": 0
  },
  {
    "ea": "0x14011e2f8",
    "module": "msvcrt",
    "name": "__CxxFrameHandler3",
    "ordinal": 0
  },
  {
    "ea": "0x14011e300",
    "module": "msvcrt",
    "name": "wcstok",
    "ordinal": 0
  },
  {
    "ea": "0x14011e308",
    "module": "msvcrt",
    "name": "realloc",
    "ordinal": 0
  },
  {
    "ea": "0x14011e310",
    "module": "msvcrt",
    "name": "_errno",
    "ordinal": 0
  },
  {
    "ea": "0x14011e318",
    "module": "msvcrt",
    "name": "_onexit",
    "ordinal": 0
  },
  {
    "ea": "0x14011e320",
    "module": "msvcrt",
    "name": "__dllonexit",
    "ordinal": 0
  },
  {
    "ea": "0x14011e328",
    "module": "msvcrt",
    "name": "_unlock",
    "ordinal": 0
  },
  {
    "ea": "0x14011e330",
    "module": "msvcrt",
    "name": "_lock",
    "ordinal": 0
  },
  {
    "ea": "0x14011e338",
    "module": "msvcrt",
    "name": "_commode",
    "ordinal": 0
  },
  {
    "ea": "0x14011e340",
    "module": "msvcrt",
    "name": "_fmode",
    "ordinal": 0
  },
  {
    "ea": "0x14011e348",
    "module": "msvcrt",
    "name": "_acmdln",
    "ordinal": 0
  },
  {
    "ea": "0x14011e350",
    "module": "msvcrt",
    "name": "memset",
    "ordinal": 0
  },
  {
    "ea": "0x14011e358",
    "module": "msvcrt",
    "name": "_initterm",
    "ordinal": 0
  },
  {
    "ea": "0x14011e360",
    "module": "msvcrt",
    "name": "__setusermatherr",
    "ordinal": 0
  },
  {
    "ea": "0x14011e368",
    "module": "msvcrt",
    "name": "_ismbblead",
    "ordinal": 0
  },
  {
    "ea": "0x14011e370",
    "module": "msvcrt",
    "name": "_cexit",
    "ordinal": 0
  },
  {
    "ea": "0x14011e378",
    "module": "msvcrt",
    "name": "_exit",
    "ordinal": 0
  },
  {
    "ea": "0x14011e380",
    "module": "msvcrt",
    "name": "exit",
    "ordinal": 0
  },
  {
    "ea": "0x14011e388",
    "module": "msvcrt",
    "name": "__set_app_type",
    "ordinal": 0
  },
  {
    "ea": "0x14011e390",
    "module": "msvcrt",
    "name": "__getmainargs",
    "ordinal": 0
  },
  {
    "ea": "0x14011e398",
    "module": "msvcrt",
    "name": "_amsg_exit",
    "ordinal": 0
  },
  {
    "ea": "0x14011e3a0",
    "module": "msvcrt",
    "name": "_XcptFilter",
    "ordinal": 0
  },
  {
    "ea": "0x14011e3a8",
    "module": "msvcrt",
    "name": "_ltow_s",
    "ordinal": 0
  },
  {
    "ea": "0x14011e3b0",
    "module": "msvcrt",
    "name": "wcscmp",
    "ordinal": 0
  },
  {
    "ea": "0x14011e3b8",
    "module": "msvcrt",
    "name": "towlower",
    "ordinal": 0
  },
  {
    "ea": "0x14011e3c0",
    "module": "msvcrt",
    "name": "wcstol",
    "ordinal": 0
  },
  {
    "ea": "0x14011e3c8",
    "module": "msvcrt",
    "name": "iswspace",
    "ordinal": 0
  },
  {
    "ea": "0x14011e3d0",
    "module": "msvcrt",
    "name": "toupper",
    "ordinal": 0
  },
  {
    "ea": "0x14011e3d8",
    "module": "msvcrt",
    "name": "wcstombs_s",
    "ordinal": 0
  },
  {
    "ea": "0x14011e3e0",
    "module": "msvcrt",
    "name": "_itow_s",
    "ordinal": 0
  },
  {
    "ea": "0x14011e3e8",
    "module": "msvcrt",
    "name": "memcpy",
    "ordinal": 0
  },
  {
    "ea": "0x14011e3f0",
    "module": "msvcrt",
    "name": "??1exception@@UEAA@XZ",
    "ordinal": 0
  },
  {
    "ea": "0x14011e3f8",
    "module": "msvcrt",
    "name": "??0exception@@QEAA@AEBV0@@Z",
    "ordinal": 0
  },
  {
    "ea": "0x14011e400",
    "module": "msvcrt",
    "name": "??0exception@@QEAA@XZ",
    "ordinal": 0
  },
  {
    "ea": "0x14011e408",
    "module": "msvcrt",
    "name": "??1type_info@@UEAA@XZ",
    "ordinal": 0
  },
  {
    "ea": "0x14011e410",
    "module": "msvcrt",
    "name": "calloc",
    "ordinal": 0
  },
  {
    "ea": "0x14011e418",
    "module": "msvcrt",
    "name": "_CxxThrowException",
    "ordinal": 0
  },
  {
    "ea": "0x14011e420",
    "module": "msvcrt",
    "name": "wcsftime",
    "ordinal": 0
  },
  {
    "ea": "0x14011e428",
    "module": "msvcrt",
    "name": "gmtime",
    "ordinal": 0
  },
  {
    "ea": "0x14011e430",
    "module": "msvcrt",
    "name": "time",
    "ordinal": 0
  },
  {
    "ea": "0x14011e438",
    "module": "msvcrt",
    "name": "wcsncat_s",
    "ordinal": 0
  },
  {
    "ea": "0x14011e440",
    "module": "msvcrt",
    "name": "memmove",
    "ordinal": 0
  },
  {
    "ea": "0x14011e448",
    "module": "msvcrt",
    "name": "_vsnwprintf",
    "ordinal": 0
  },
  {
    "ea": "0x14011e450",
    "module": "msvcrt",
    "name": "memcpy_s",
    "ordinal": 0
  },
  {
    "ea": "0x14011e458",
    "module": "msvcrt",
    "name": "__C_specific_handler",
    "ordinal": 0
  },
  {
    "ea": "0x14011e460",
    "module": "msvcrt",
    "name": "wcsncpy_s",
    "ordinal": 0
  },
  {
    "ea": "0x14011e468",
    "module": "msvcrt",
    "name": "malloc",
    "ordinal": 0
  },
  {
    "ea": "0x14011e470",
    "module": "msvcrt",
    "name": "free",
    "ordinal": 0
  },
  {
    "ea": "0x14011e478",
    "module": "msvcrt",
    "name": "wcscpy_s",
    "ordinal": 0
  },
  {
    "ea": "0x14011e480",
    "module": "msvcrt",
    "name": "wcscat_s",
    "ordinal": 0
  },
  {
    "ea": "0x14011e488",
    "module": "msvcrt",
    "name": "_purecall",
    "ordinal": 0
  },
  {
    "ea": "0x14011e490",
    "module": "msvcrt",
    "name": "_wcsicmp",
    "ordinal": 0
  },
  {
    "ea": "0x14011e498",
    "module": "msvcrt",
    "name": "wcstok_s",
    "ordinal": 0
  },
  {
    "ea": "0x14011e4a0",
    "module": "msvcrt",
    "name": "_wtol",
    "ordinal": 0
  },
  {
    "ea": "0x14011e4a8",
    "module": "msvcrt",
    "name": "wcsrchr",
    "ordinal": 0
  },
  {
    "ea": "0x14011e4b0",
    "module": "msvcrt",
    "name": "_wtoi",
    "ordinal": 0
  },
  {
    "ea": "0x14011e4b8",
    "module": "msvcrt",
    "name": "wcsstr",
    "ordinal": 0
  },
  {
    "ea": "0x14011e4c0",
    "module": "msvcrt",
    "name": "swscanf_s",
    "ordinal": 0
  },
  {
    "ea": "0x14011e4c8",
    "module": "msvcrt",
    "name": "_vsnprintf",
    "ordinal": 0
  },
  {
    "ea": "0x14011e4d0",
    "module": "msvcrt",
    "name": "_wcsnicmp",
    "ordinal": 0
  },
  {
    "ea": "0x14011e4d8",
    "module": "msvcrt",
    "name": "_callnewh",
    "ordinal": 0
  },
  {
    "ea": "0x14011e4e0",
    "module": "msvcrt",
    "name": "iswdigit",
    "ordinal": 0
  },
  {
    "ea": "0x14011e4e8",
    "module": "msvcrt",
    "name": "wcstoul",
    "ordinal": 0
  },
  {
    "ea": "0x14011e4f0",
    "module": "msvcrt",
    "name": "pow",
    "ordinal": 0
  },
  {
    "ea": "0x14011e4f8",
    "module": "msvcrt",
    "name": "towupper",
    "ordinal": 0
  },
  {
    "ea": "0x14011e500",
    "module": "msvcrt",
    "name": "wcschr",
    "ordinal": 0
  },
  {
    "ea": "0x14011e508",
    "module": "msvcrt",
    "name": "_wcslwr_s",
    "ordinal": 0
  },
  {
    "ea": "0x14011e510",
    "module": "msvcrt",
    "name": "wcsncmp",
    "ordinal": 0
  },
  {
    "ea": "0x14011ddd0",
    "module": "SHLWAPI",
    "name": "PathIsNetworkPathW",
    "ordinal": 0
  },
  {
    "ea": "0x14011ddd8",
    "module": "SHLWAPI",
    "name": "PathFindExtensionW",
    "ordinal": 0
  },
  {
    "ea": "0x14011dde0",
    "module": "SHLWAPI",
    "name": "PathStripPathW",
    "ordinal": 0
  },
  {
    "ea": "0x14011dde8",
    "module": "SHLWAPI",
    "name": "PathRemoveFileSpecW",
    "ordinal": 0
  },
  {
    "ea": "0x14011ddf0",
    "module": "SHLWAPI",
    "name": "PathAppendW",
    "ordinal": 0
  },
  {
    "ea": "0x14011ddf8",
    "module": "SHLWAPI",
    "name": "PathFindFileNameW",
    "ordinal": 0
  },
  {
    "ea": "0x14011de00",
    "module": "SHLWAPI",
    "name": "StrStrIW",
    "ordinal": 0
  },
  {
    "ea": "0x14011ddc8",
    "module": "SHLWAPI",
    "name": "__imp_ShellMessageBoxW",
    "ordinal": 388
  },
  {
    "ea": "0x14011e520",
    "module": "ntdll",
    "name": "VerSetConditionMask",
    "ordinal": 0
  },
  {
    "ea": "0x14011e528",
    "module": "ntdll",
    "name": "RtlCaptureContext",
    "ordinal": 0
  },
  {
    "ea": "0x14011e530",
    "module": "ntdll",
    "name": "RtlLookupFunctionEntry",
    "ordinal": 0
  },
  {
    "ea": "0x14011e538",
    "module": "ntdll",
    "name": "RtlVirtualUnwind",
    "ordinal": 0
  },
  {
    "ea": "0x14011e540",
    "module": "ntdll",
    "name": "RtlNtStatusToDosError",
    "ordinal": 0
  },
  {
    "ea": "0x14011e548",
    "module": "ntdll",
    "name": "RtlInitString",
    "ordinal": 0
  },
  {
    "ea": "0x14011e290",
    "module": "api-ms-win-core-featurestaging-l1-1-0",
    "name": "SubscribeFeatureStateChangeNotification",
    "ordinal": 0
  },
  {
    "ea": "0x14011e298",
    "module": "api-ms-win-core-featurestaging-l1-1-0",
    "name": "RecordFeatureUsage",
    "ordinal": 0
  },
  {
    "ea": "0x14011e2a0",
    "module": "api-ms-win-core-featurestaging-l1-1-0",
    "name": "GetFeatureEnabledState",
    "ordinal": 0
  },
  {
    "ea": "0x14011e2a8",
    "module": "api-ms-win-core-featurestaging-l1-1-0",
    "name": "UnsubscribeFeatureStateChangeNotification",
    "ordinal": 0
  },
  {
    "ea": "0x14011e248",
    "module": "VERSION",
    "name": "GetFileVersionInfoW",
    "ordinal": 0
  },
  {
    "ea": "0x14011e250",
    "module": "VERSION",
    "name": "GetFileVersionInfoSizeW",
    "ordinal": 0
  },
  {
    "ea": "0x14011e258",
    "module": "VERSION",
    "name": "VerQueryValueW",
    "ordinal": 0
  },
  {
    "ea": "0x14011ddb0",
    "module": "SHCORE",
    "name": "SHStrDupW",
    "ordinal": 0
  },
  {
    "ea": "0x14011ddb8",
    "module": "SHCORE",
    "name": "SHCreateMemStream",
    "ordinal": 0
  },
  {
    "ea": "0x14011e2d0",
    "module": "dwmapi",
    "name": "DwmGetWindowAttribute",
    "ordinal": 0
  },
  {
    "ea": "0x14011e268",
    "module": "WTSAPI32",
    "name": "WTSFreeMemory",
    "ordinal": 0
  },
  {
    "ea": "0x14011e270",
    "module": "WTSAPI32",
    "name": "WTSQuerySessionInformationW",
    "ordinal": 0
  },
  {
    "ea": "0x14011e278",
    "module": "WTSAPI32",
    "name": "WTSCloseServer",
    "ordinal": 0
  },
  {
    "ea": "0x14011e280",
    "module": "WTSAPI32",
    "name": "WTSOpenServerW",
    "ordinal": 0
  },
  {
    "ea": "0x14011d8a0",
    "module": "KERNEL32",
    "name": "GetCommandLineW",
    "ordinal": 0
  },
  {
    "ea": "0x14011d8a8",
    "module": "KERNEL32",
    "name": "TlsSetValue",
    "ordinal": 0
  },
  {
    "ea": "0x14011d8b0",
    "module": "KERNEL32",
    "name": "QueryPerformanceFrequency",
    "ordinal": 0
  },
  {
    "ea": "0x14011d8b8",
    "module": "KERNEL32",
    "name": "GetSystemTime",
    "ordinal": 0
  },
  {
    "ea": "0x14011d8c0",
    "module": "KERNEL32",
    "name": "TrySubmitThreadpoolCallback",
    "ordinal": 0
  },
  {
    "ea": "0x14011d8c8",
    "module": "KERNEL32",
    "name": "SetThreadpoolThreadMinimum",
    "ordinal": 0
  },
  {
    "ea": "0x14011d8d0",
    "module": "KERNEL32",
    "name": "SetThreadpoolThreadMaximum",
    "ordinal": 0
  },
  {
    "ea": "0x14011d8d8",
    "module": "KERNEL32",
    "name": "InitializeCriticalSectionAndSpinCount",
    "ordinal": 0
  },
  {
    "ea": "0x14011d8e0",
    "module": "KERNEL32",
    "name": "FindResourceW",
    "ordinal": 0
  },
  {
    "ea": "0x14011d8e8",
    "module": "KERNEL32",
    "name": "LoadLibraryA",
    "ordinal": 0
  },
  {
    "ea": "0x14011d8f0",
    "module": "KERNEL32",
    "name": "GetProcessId",
    "ordinal": 0
  },
  {
    "ea": "0x14011d8f8",
    "module": "KERNEL32",
    "name": "TerminateThread",
    "ordinal": 0
  },
  {
    "ea": "0x14011d900",
    "module": "KERNEL32",
    "name": "ProcessIdToSessionId",
    "ordinal": 0
  },
  {
    "ea": "0x14011d908",
    "module": "KERNEL32",
    "name": "GetComputerNameW",
    "ordinal": 0
  },
  {
    "ea": "0x14011d910",
    "module": "KERNEL32",
    "name": "InitOnceExecuteOnce",
    "ordinal": 0
  },
  {
    "ea": "0x14011d918",
    "module": "KERNEL32",
    "name": "ExpandEnvironmentStringsW",
    "ordinal": 0
  },
  {
    "ea": "0x14011d920",
    "module": "KERNEL32",
    "name": "CreateEventExW",
    "ordinal": 0
  },
  {
    "ea": "0x14011d928",
    "module": "KERNEL32",
    "name": "LockResource",
    "ordinal": 0
  },
  {
    "ea": "0x14011d930",
    "module": "KERNEL32",
    "name": "IsThreadpoolTimerSet",
    "ordinal": 0
  },
  {
    "ea": "0x14011d938",
    "module": "KERNEL32",
    "name": "CloseThreadpoolCleanupGroup",
    "ordinal": 0
  },
  {
    "ea": "0x14011d940",
    "module": "KERNEL32",
    "name": "CloseThreadpoolCleanupGroupMembers",
    "ordinal": 0
  },
  {
    "ea": "0x14011d948",
    "module": "KERNEL32",
    "name": "SetThreadpoolWait",
    "ordinal": 0
  },
  {
    "ea": "0x14011d950",
    "module": "KERNEL32",
    "name": "CreateThreadpoolWait",
    "ordinal": 0
  },
  {
    "ea": "0x14011d958",
    "module": "KERNEL32",
    "name": "CreateThreadpoolCleanupGroup",
    "ordinal": 0
  },
  {
    "ea": "0x14011d960",
    "module": "KERNEL32",
    "name": "CloseThreadpool",
    "ordinal": 0
  },
  {
    "ea": "0x14011d968",
    "module": "KERNEL32",
    "name": "CreateThreadpool",
    "ordinal": 0
  },
  {
    "ea": "0x14011d970",
    "module": "KERNEL32",
    "name": "GetOverlappedResult",
    "ordinal": 0
  },
  {
    "ea": "0x14011d978",
    "module": "KERNEL32",
    "name": "CloseThreadpoolWork",
    "ordinal": 0
  },
  {
    "ea": "0x14011d980",
    "module": "KERNEL32",
    "name": "SubmitThreadpoolWork",
    "ordinal": 0
  },
  {
    "ea": "0x14011d988",
    "module": "KERNEL32",
    "name": "CreateThreadpoolWork",
    "ordinal": 0
  },
  {
    "ea": "0x14011d990",
    "module": "KERNEL32",
    "name": "DisconnectNamedPipe",
    "ordinal": 0
  },
  {
    "ea": "0x14011d998",
    "module": "KERNEL32",
    "name": "CreateThreadpoolIo",
    "ordinal": 0
  },
  {
    "ea": "0x14011d9a0",
    "module": "KERNEL32",
    "name": "CancelThreadpoolIo",
    "ordinal": 0
  },
  {
    "ea": "0x14011d9a8",
    "module": "KERNEL32",
    "name": "StartThreadpoolIo",
    "ordinal": 0
  },
  {
    "ea": "0x14011d9b0",
    "module": "KERNEL32",
    "name": "CloseThreadpoolIo",
    "ordinal": 0
  },
  {
    "ea": "0x14011d9b8",
    "module": "KERNEL32",
    "name": "WaitForThreadpoolIoCallbacks",
    "ordinal": 0
  },
  {
    "ea": "0x14011d9c0",
    "module": "KERNEL32",
    "name": "QueueUserWorkItem",
    "ordinal": 0
  },
  {
    "ea": "0x14011d9c8",
    "module": "KERNEL32",
    "name": "ResetEvent",
    "ordinal": 0
  },
  {
    "ea": "0x14011d9d0",
    "module": "KERNEL32",
    "name": "CreateSemaphoreW",
    "ordinal": 0
  },
  {
    "ea": "0x14011d9d8",
    "module": "KERNEL32",
    "name": "FreeLibraryAndExitThread",
    "ordinal": 0
  },
  {
    "ea": "0x14011d9e0",
    "module": "KERNEL32",
    "name": "GetExitCodeThread",
    "ordinal": 0
  },
  {
    "ea": "0x14011d9e8",
    "module": "KERNEL32",
    "name": "WaitForMultipleObjects",
    "ordinal": 0
  },
  {
    "ea": "0x14011d9f0",
    "module": "KERNEL32",
    "name": "CancelWaitableTimer",
    "ordinal": 0
  },
  {
    "ea": "0x14011d9f8",
    "module": "KERNEL32",
    "name": "SetWaitableTimer",
    "ordinal": 0
  },
  {
    "ea": "0x14011da00",
    "module": "KERNEL32",
    "name": "CreateWaitableTimerExW",
    "ordinal": 0
  },
  {
    "ea": "0x14011da08",
    "module": "KERNEL32",
    "name": "OutputDebugStringA",
    "ordinal": 0
  },
  {
    "ea": "0x14011da10",
    "module": "KERNEL32",
    "name": "GetTickCount",
    "ordinal": 0
  },
  {
    "ea": "0x14011da18",
    "module": "KERNEL32",
    "name": "GetSystemTimeAsFileTime",
    "ordinal": 0
  },
  {
    "ea": "0x14011da20",
    "module": "KERNEL32",
    "name": "QueryPerformanceCounter",
    "ordinal": 0
  },
  {
    "ea": "0x14011da28",
    "module": "KERNEL32",
    "name": "SetUnhandledExceptionFilter",
    "ordinal": 0
  },
  {
    "ea": "0x14011da30",
    "module": "KERNEL32",
    "name": "UnhandledExceptionFilter",
    "ordinal": 0
  },
  {
    "ea": "0x14011da38",
    "module": "KERNEL32",
    "name": "GetStartupInfoW",
    "ordinal": 0
  },
  {
    "ea": "0x14011da40",
    "module": "KERNEL32",
    "name": "WideCharToMultiByte",
    "ordinal": 0
  },
  {
    "ea": "0x14011da48",
    "module": "KERNEL32",
    "name": "K32GetModuleFileNameExW",
    "ordinal": 0
  },
  {
    "ea": "0x14011da50",
    "module": "KERNEL32",
    "name": "Sleep",
    "ordinal": 0
  },
  {
    "ea": "0x14011da58",
    "module": "KERNEL32",
    "name": "HeapSetInformation",
    "ordinal": 0
  },
  {
    "ea": "0x14011da60",
    "module": "KERNEL32",
    "name": "GetSystemDirectoryW",
    "ordinal": 0
  },
  {
    "ea": "0x14011da68",
    "module": "KERNEL32",
    "name": "CreateProcessW",
    "ordinal": 0
  },
  {
    "ea": "0x14011da70",
    "module": "KERNEL32",
    "name": "GetCurrentThread",
    "ordinal": 0
  },
  {
    "ea": "0x14011da78",
    "module": "KERNEL32",
    "name": "GetTickCount64",
    "ordinal": 0
  },
  {
    "ea": "0x14011da80",
    "module": "KERNEL32",
    "name": "WriteFile",
    "ordinal": 0
  },
  {
    "ea": "0x14011da88",
    "module": "KERNEL32",
    "name": "VerifyVersionInfoW",
    "ordinal": 0
  },
  {
    "ea": "0x14011da90",
    "module": "KERNEL32",
    "name": "FindClose",
    "ordinal": 0
  },
  {
    "ea": "0x14011da98",
    "module": "KERNEL32",
    "name": "FindNextFileW",
    "ordinal": 0
  },
  {
    "ea": "0x14011daa0",
    "module": "KERNEL32",
    "name": "FindFirstFileW",
    "ordinal": 0
  },
  {
    "ea": "0x14011daa8",
    "module": "KERNEL32",
    "name": "GetFileAttributesExW",
    "ordinal": 0
  },
  {
    "ea": "0x14011dab0",
    "module": "KERNEL32",
    "name": "GetTempPathW",
    "ordinal": 0
  },
  {
    "ea": "0x14011dab8",
    "module": "KERNEL32",
    "name": "CompareStringW",
    "ordinal": 0
  },
  {
    "ea": "0x14011dac0",
    "module": "KERNEL32",
    "name": "SetFilePointer",
    "ordinal": 0
  },
  {
    "ea": "0x14011dac8",
    "module": "KERNEL32",
    "name": "GetACP",
    "ordinal": 0
  },
  {
    "ea": "0x14011dad0",
    "module": "KERNEL32",
    "name": "GetFullPathNameW",
    "ordinal": 0
  },
  {
    "ea": "0x14011dad8",
    "module": "KERNEL32",
    "name": "GetFileAttributesW",
    "ordinal": 0
  },
  {
    "ea": "0x14011dae0",
    "module": "KERNEL32",
    "name": "LocalAlloc",
    "ordinal": 0
  },
  {
    "ea": "0x14011dae8",
    "module": "KERNEL32",
    "name": "CompareStringOrdinal",
    "ordinal": 0
  },
  {
    "ea": "0x14011daf0",
    "module": "KERNEL32",
    "name": "CreateDirectoryW",
    "ordinal": 0
  },
  {
    "ea": "0x14011daf8",
    "module": "KERNEL32",
    "name": "SearchPathW",
    "ordinal": 0
  },
  {
    "ea": "0x14011db00",
    "module": "KERNEL32",
    "name": "GetCurrentDirectoryW",
    "ordinal": 0
  },
  {
    "ea": "0x14011db08",
    "module": "KERNEL32",
    "name": "LocalFree",
    "ordinal": 0
  },
  {
    "ea": "0x14011db10",
    "module": "KERNEL32",
    "name": "LoadLibraryW",
    "ordinal": 0
  },
  {
    "ea": "0x14011db18",
    "module": "KERNEL32",
    "name": "CreateThreadpoolTimer",
    "ordinal": 0
  },
  {
    "ea": "0x14011db20",
    "module": "KERNEL32",
    "name": "GetCurrentProcess",
    "ordinal": 0
  },
  {
    "ea": "0x14011db28",
    "module": "KERNEL32",
    "name": "TerminateProcess",
    "ordinal": 0
  },
  {
    "ea": "0x14011db30",
    "module": "KERNEL32",
    "name": "GetStartupInfoA",
    "ordinal": 0
  },
  {
    "ea": "0x14011db38",
    "module": "KERNEL32",
    "name": "lstrcmpW",
    "ordinal": 0
  },
  {
    "ea": "0x14011db40",
    "module": "KERNEL32",
    "name": "GetVersionExA",
    "ordinal": 0
  },
  {
    "ea": "0x14011db48",
    "module": "KERNEL32",
    "name": "MulDiv",
    "ordinal": 0
  },
  {
    "ea": "0x14011db50",
    "module": "KERNEL32",
    "name": "GetVersionExW",
    "ordinal": 0
  },
  {
    "ea": "0x14011db58",
    "module": "KERNEL32",
    "name": "ReadFile",
    "ordinal": 0
  },
  {
    "ea": "0x14011db60",
    "module": "KERNEL32",
    "name": "GetFileSize",
    "ordinal": 0
  },
  {
    "ea": "0x14011db68",
    "module": "KERNEL32",
    "name": "CreateFileW",
    "ordinal": 0
  },
  {
    "ea": "0x14011db70",
    "module": "KERNEL32",
    "name": "GetDateFormatW",
    "ordinal": 0
  },
  {
    "ea": "0x14011db78",
    "module": "KERNEL32",
    "name": "GetTimeFormatW",
    "ordinal": 0
  },
  {
    "ea": "0x14011db80",
    "module": "KERNEL32",
    "name": "GetLocalTime",
    "ordinal": 0
  },
  {
    "ea": "0x14011db88",
    "module": "KERNEL32",
    "name": "DeleteFileW",
    "ordinal": 0
  },
  {
    "ea": "0x14011db90",
    "module": "KERNEL32",
    "name": "CreateThread",
    "ordinal": 0
  },
  {
    "ea": "0x14011db98",
    "module": "KERNEL32",
    "name": "CreateEventW",
    "ordinal": 0
  },
  {
    "ea": "0x14011dba0",
    "module": "KERNEL32",
    "name": "SetEvent",
    "ordinal": 0
  },
  {
    "ea": "0x14011dba8",
    "module": "KERNEL32",
    "name": "InitializeCriticalSection",
    "ordinal": 0
  },
  {
    "ea": "0x14011dbb0",
    "module": "KERNEL32",
    "name": "GetModuleHandleExA",
    "ordinal": 0
  },
  {
    "ea": "0x14011dbb8",
    "module": "KERNEL32",
    "name": "GetModuleFileNameW",
    "ordinal": 0
  },
  {
    "ea": "0x14011dbc0",
    "module": "KERNEL32",
    "name": "FindResourceExW",
    "ordinal": 0
  },
  {
    "ea": "0x14011dbc8",
    "module": "KERNEL32",
    "name": "LoadResource",
    "ordinal": 0
  },
  {
    "ea": "0x14011dbd0",
    "module": "KERNEL32",
    "name": "SizeofResource",
    "ordinal": 0
  },
  {
    "ea": "0x14011dbd8",
    "module": "KERNEL32",
    "name": "SystemTimeToFileTime",
    "ordinal": 0
  },
  {
    "ea": "0x14011dbe0",
    "module": "KERNEL32",
    "name": "MapViewOfFile",
    "ordinal": 0
  },
  {
    "ea": "0x14011dbe8",
    "module": "KERNEL32",
    "name": "CreateFileMappingW",
    "ordinal": 0
  },
  {
    "ea": "0x14011dbf0",
    "module": "KERNEL32",
    "name": "LCIDToLocaleName",
    "ordinal": 0
  },
  {
    "ea": "0x14011dbf8",
    "module": "KERNEL32",
    "name": "UnmapViewOfFile",
    "ordinal": 0
  },
  {
    "ea": "0x14011dc00",
    "module": "KERNEL32",
    "name": "GetLocaleInfoW",
    "ordinal": 0
  },
  {
    "ea": "0x14011dc08",
    "module": "KERNEL32",
    "name": "GetUserDefaultUILanguage",
    "ordinal": 0
  },
  {
    "ea": "0x14011dc10",
    "module": "KERNEL32",
    "name": "GetLocaleInfoEx",
    "ordinal": 0
  },
  {
    "ea": "0x14011dc18",
    "module": "KERNEL32",
    "name": "GetSystemDefaultUILanguage",
    "ordinal": 0
  },
  {
    "ea": "0x14011dc20",
    "module": "KERNEL32",
    "name": "HeapDestroy",
    "ordinal": 0
  },
  {
    "ea": "0x14011dc28",
    "module": "KERNEL32",
    "name": "HeapReAlloc",
    "ordinal": 0
  },
  {
    "ea": "0x14011dc30",
    "module": "KERNEL32",
    "name": "HeapSize",
    "ordinal": 0
  },
  {
    "ea": "0x14011dc38",
    "module": "KERNEL32",
    "name": "DelayLoadFailureHook",
    "ordinal": 0
  },
  {
    "ea": "0x14011dc40",
    "module": "KERNEL32",
    "name": "ResolveDelayLoadedAPI",
    "ordinal": 0
  },
  {
    "ea": "0x14011dc48",
    "module": "KERNEL32",
    "name": "MultiByteToWideChar",
    "ordinal": 0
  },
  {
    "ea": "0x14011dc50",
    "module": "KERNEL32",
    "name": "lstrcmpiW",
    "ordinal": 0
  },
  {
    "ea": "0x14011dc58",
    "module": "KERNEL32",
    "name": "LoadLibraryExW",
    "ordinal": 0
  },
  {
    "ea": "0x14011dc60",
    "module": "KERNEL32",
    "name": "FreeLibrary",
    "ordinal": 0
  },
  {
    "ea": "0x14011dc68",
    "module": "KERNEL32",
    "name": "EnterCriticalSection",
    "ordinal": 0
  },
  {
    "ea": "0x14011dc70",
    "module": "KERNEL32",
    "name": "DeleteCriticalSection",
    "ordinal": 0
  },
  {
    "ea": "0x14011dc78",
    "module": "KERNEL32",
    "name": "LeaveCriticalSection",
    "ordinal": 0
  },
  {
    "ea": "0x14011dc80",
    "module": "KERNEL32",
    "name": "RaiseException",
    "ordinal": 0
  },
  {
    "ea": "0x14011dc88",
    "module": "KERNEL32",
    "name": "IsDebuggerPresent",
    "ordinal": 0
  },
  {
    "ea": "0x14011dc90",
    "module": "KERNEL32",
    "name": "DebugBreak",
    "ordinal": 0
  },
  {
    "ea": "0x14011dc98",
    "module": "KERNEL32",
    "name": "GetModuleHandleW",
    "ordinal": 0
  },
  {
    "ea": "0x14011dca0",
    "module": "KERNEL32",
    "name": "GetProcessHeap",
    "ordinal": 0
  },
  {
    "ea": "0x14011dca8",
    "module": "KERNEL32",
    "name": "GetCurrentProcessId",
    "ordinal": 0
  },
  {
    "ea": "0x14011dcb0",
    "module": "KERNEL32",
    "name": "CreateMutexExW",
    "ordinal": 0
  },
  {
    "ea": "0x14011dcb8",
    "module": "KERNEL32",
    "name": "GetProcAddress",
    "ordinal": 0
  },
  {
    "ea": "0x14011dcc0",
    "module": "KERNEL32",
    "name": "HeapAlloc",
    "ordinal": 0
  },
  {
    "ea": "0x14011dcc8",
    "module": "KERNEL32",
    "name": "SetThreadpoolTimer",
    "ordinal": 0
  },
  {
    "ea": "0x14011dcd0",
    "module": "KERNEL32",
    "name": "CloseHandle",
    "ordinal": 0
  },
  {
    "ea": "0x14011dcd8",
    "module": "KERNEL32",
    "name": "OpenSemaphoreW",
    "ordinal": 0
  },
  {
    "ea": "0x14011dce0",
    "module": "KERNEL32",
    "name": "WaitForSingleObjectEx",
    "ordinal": 0
  },
  {
    "ea": "0x14011dce8",
    "module": "KERNEL32",
    "name": "AcquireSRWLockExclusive",
    "ordinal": 0
  },
  {
    "ea": "0x14011dcf0",
    "module": "KERNEL32",
    "name": "CloseThreadpoolTimer",
    "ordinal": 0
  },
  {
    "ea": "0x14011dcf8",
    "module": "KERNEL32",
    "name": "OutputDebugStringW",
    "ordinal": 0
  },
  {
    "ea": "0x14011dd00",
    "module": "KERNEL32",
    "name": "ReleaseSRWLockExclusive",
    "ordinal": 0
  },
  {
    "ea": "0x14011dd08",
    "module": "KERNEL32",
    "name": "GetLastError",
    "ordinal": 0
  },
  {
    "ea": "0x14011dd10",
    "module": "KERNEL32",
    "name": "FormatMessageW",
    "ordinal": 0
  },
  {
    "ea": "0x14011dd18",
    "module": "KERNEL32",
    "name": "ReleaseMutex",
    "ordinal": 0
  },
  {
    "ea": "0x14011dd20",
    "module": "KERNEL32",
    "name": "GetCurrentThreadId",
    "ordinal": 0
  },
  {
    "ea": "0x14011dd28",
    "module": "KERNEL32",
    "name": "WaitForSingleObject",
    "ordinal": 0
  },
  {
    "ea": "0x14011dd30",
    "module": "KERNEL32",
    "name": "WaitForThreadpoolTimerCallbacks",
    "ordinal": 0
  },
  {
    "ea": "0x14011dd38",
    "module": "KERNEL32",
    "name": "GetModuleHandleExW",
    "ordinal": 0
  },
  {
    "ea": "0x14011dd40",
    "module": "KERNEL32",
    "name": "ReleaseSemaphore",
    "ordinal": 0
  },
  {
    "ea": "0x14011dd48",
    "module": "KERNEL32",
    "name": "SetLastError",
    "ordinal": 0
  },
  {
    "ea": "0x14011dd50",
    "module": "KERNEL32",
    "name": "HeapFree",
    "ordinal": 0
  },
  {
    "ea": "0x14011dd58",
    "module": "KERNEL32",
    "name": "CreateSemaphoreExW",
    "ordinal": 0
  },
  {
    "ea": "0x14011dd60",
    "module": "KERNEL32",
    "name": "GetModuleFileNameA",
    "ordinal": 0
  },
  {
    "ea": "0x14011dd68",
    "module": "KERNEL32",
    "name": "TlsAlloc",
    "ordinal": 0
  },
  {
    "ea": "0x14011dd70",
    "module": "KERNEL32",
    "name": "GetSystemInfo",
    "ordinal": 0
  },
  {
    "ea": "0x14011dd78",
    "module": "KERNEL32",
    "name": "SwitchToThread",
    "ordinal": 0
  },
  {
    "ea": "0x14011dd80",
    "module": "KERNEL32",
    "name": "TlsGetValue",
    "ordinal": 0
  },
  {
    "ea": "0x14011dd88",
    "module": "KERNEL32",
    "name": "TlsFree",
    "ordinal": 0
  },
  {
    "ea": "0x14011dd90",
    "module": "KERNEL32",
    "name": "OpenThread",
    "ordinal": 0
  },
  {
    "ea": "0x14011dda0",
    "module": "Normaliz",
    "name": "IdnToAscii",
    "ordinal": 0
  },
  {
    "ea": "0x14011e2b8",
    "module": "api-ms-win-core-path-l1-1-0",
    "name": "PathAllocCombine",
    "ordinal": 0
  },
  {
    "ea": "0x14011e2c0",
    "module": "api-ms-win-core-path-l1-1-0",
    "name": "PathCchRemoveExtension",
    "ordinal": 0
  },
  {
    "ea": "0x14015f310",
    "module": "GDI32",
    "name": "CreateDIBSection",
    "ordinal": 0
  },
  {
    "ea": "0x14015f318",
    "module": "GDI32",
    "name": "CreateDCW",
    "ordinal": 0
  },
  {
    "ea": "0x14015f320",
    "module": "GDI32",
    "name": "UpdateColors",
    "ordinal": 0
  },
  {
    "ea": "0x14015f328",
    "module": "GDI32",
    "name": "TranslateCharsetInfo",
    "ordinal": 0
  },
  {
    "ea": "0x14015f330",
    "module": "GDI32",
    "name": "SetMapMode",
    "ordinal": 0
  },
  {
    "ea": "0x14015f338",
    "module": "GDI32",
    "name": "DeleteDC",
    "ordinal": 0
  },
  {
    "ea": "0x14015f340",
    "module": "GDI32",
    "name": "StretchBlt",
    "ordinal": 0
  },
  {
    "ea": "0x14015f348",
    "module": "GDI32",
    "name": "BitBlt",
    "ordinal": 0
  },
  {
    "ea": "0x14015f350",
    "module": "GDI32",
    "name": "CreateCompatibleBitmap",
    "ordinal": 0
  },
  {
    "ea": "0x14015f358",
    "module": "GDI32",
    "name": "CreateCompatibleDC",
    "ordinal": 0
  },
  {
    "ea": "0x14015f360",
    "module": "GDI32",
    "name": "GetDeviceCaps",
    "ordinal": 0
  },
  {
    "ea": "0x14015f368",
    "module": "GDI32",
    "name": "GetDIBColorTable",
    "ordinal": 0
  },
  {
    "ea": "0x14015f370",
    "module": "GDI32",
    "name": "CreatePalette",
    "ordinal": 0
  },
  {
    "ea": "0x14015f378",
    "module": "GDI32",
    "name": "SetTextColor",
    "ordinal": 0
  },
  {
    "ea": "0x14015f380",
    "module": "GDI32",
    "name": "SetBkMode",
    "ordinal": 0
  },
  {
    "ea": "0x14015f388",
    "module": "GDI32",
    "name": "GetObjectW",
    "ordinal": 0
  },
  {
    "ea": "0x14015f390",
    "module": "GDI32",
    "name": "PatBlt",
    "ordinal": 0
  },
  {
    "ea": "0x14015f398",
    "module": "GDI32",
    "name": "SelectObject",
    "ordinal": 0
  },
  {
    "ea": "0x14015f3a0",
    "module": "GDI32",
    "name": "CreateSolidBrush",
    "ordinal": 0
  },
  {
    "ea": "0x14015f3a8",
    "module": "GDI32",
    "name": "RealizePalette",
    "ordinal": 0
  },
  {
    "ea": "0x14015f3b0",
    "module": "GDI32",
    "name": "SelectPalette",
    "ordinal": 0
  },
  {
    "ea": "0x14015f3b8",
    "module": "GDI32",
    "name": "GetStockObject",
    "ordinal": 0
  },
  {
    "ea": "0x14015f3c0",
    "module": "GDI32",
    "name": "EqualRgn",
    "ordinal": 0
  },
  {
    "ea": "0x14015f3c8",
    "module": "GDI32",
    "name": "CombineRgn",
    "ordinal": 0
  },
  {
    "ea": "0x14015f3d0",
    "module": "GDI32",
    "name": "OffsetRgn",
    "ordinal": 0
  },
  {
    "ea": "0x14015f3d8",
    "module": "GDI32",
    "name": "GetRgnBox",
    "ordinal": 0
  },
  {
    "ea": "0x14015f3e0",
    "module": "GDI32",
    "name": "SetRectRgn",
    "ordinal": 0
  },
  {
    "ea": "0x14015f3e8",
    "module": "GDI32",
    "name": "DeleteObject",
    "ordinal": 0
  },
  {
    "ea": "0x14015f3f0",
    "module": "GDI32",
    "name": "CreateRectRgnIndirect",
    "ordinal": 0
  },
  {
    "ea": "0x14015f3f8",
    "module": "GDI32",
    "name": "FillRgn",
    "ordinal": 0
  },
  {
    "ea": "0x14015f400",
    "module": "GDI32",
    "name": "CreateFontIndirectW",
    "ordinal": 0
  },
  {
    "ea": "0x14015f408",
    "module": "GDI32",
    "name": "CreateRectRgn",
    "ordinal": 0
  },
  {
    "ea": "0x14015f7b0",
    "module": "ole32",
    "name": "StringFromIID",
    "ordinal": 0
  },
  {
    "ea": "0x14015f7b8",
    "module": "ole32",
    "name": "IIDFromString",
    "ordinal": 0
  },
  {
    "ea": "0x14015f7c0",
    "module": "ole32",
    "name": "CoCreateGuid",
    "ordinal": 0
  },
  {
    "ea": "0x14015f7c8",
    "module": "ole32",
    "name": "OleInitialize",
    "ordinal": 0
  },
  {
    "ea": "0x14015f7d0",
    "module": "ole32",
    "name": "CoRevokeClassObject",
    "ordinal": 0
  },
  {
    "ea": "0x14015f7d8",
    "module": "ole32",
    "name": "CreateItemMoniker",
    "ordinal": 0
  },
  {
    "ea": "0x14015f7e0",
    "module": "ole32",
    "name": "CLSIDFromString",
    "ordinal": 0
  },
  {
    "ea": "0x14015f7e8",
    "module": "ole32",
    "name": "CoInitialize",
    "ordinal": 0
  },
  {
    "ea": "0x14015f7f0",
    "module": "ole32",
    "name": "CoUninitialize",
    "ordinal": 0
  },
  {
    "ea": "0x14015f7f8",
    "module": "ole32",
    "name": "StringFromGUID2",
    "ordinal": 0
  },
  {
    "ea": "0x14015f800",
    "module": "ole32",
    "name": "CoRegisterClassObject",
    "ordinal": 0
  },
  {
    "ea": "0x14015f808",
    "module": "ole32",
    "name": "CoTaskMemAlloc",
    "ordinal": 0
  },
  {
    "ea": "0x14015f810",
    "module": "ole32",
    "name": "CoTaskMemRealloc",
    "ordinal": 0
  },
  {
    "ea": "0x14015f818",
    "module": "ole32",
    "name": "CoTaskMemFree",
    "ordinal": 0
  },
  {
    "ea": "0x14015f820",
    "module": "ole32",
    "name": "OleUninitialize",
    "ordinal": 0
  },
  {
    "ea": "0x14015f828",
    "module": "ole32",
    "name": "CoCreateInstance",
    "ordinal": 0
  },
  {
    "ea": "0x14015f830",
    "module": "ole32",
    "name": "GetRunningObjectTable",
    "ordinal": 0
  },
  {
    "ea": "0x14015f4f0",
    "module": "OLEAUT32",
    "name": "__imp_SysAllocString",
    "ordinal": 2
  },
  {
    "ea": "0x14015f4a0",
    "module": "OLEAUT32",
    "name": "__imp_SysAllocStringLen",
    "ordinal": 4
  },
  {
    "ea": "0x14015f488",
    "module": "OLEAUT32",
    "name": "__imp_SysFreeString",
    "ordinal": 6
  },
  {
    "ea": "0x14015f4d0",
    "module": "OLEAUT32",
    "name": "__imp_SysStringLen",
    "ordinal": 7
  },
  {
    "ea": "0x14015f490",
    "module": "OLEAUT32",
    "name": "__imp_VariantInit",
    "ordinal": 8
  },
  {
    "ea": "0x14015f498",
    "module": "OLEAUT32",
    "name": "__imp_VariantClear",
    "ordinal": 9
  },
  {
    "ea": "0x14015f4c0",
    "module": "OLEAUT32",
    "name": "__imp_VariantCopy",
    "ordinal": 10
  },
  {
    "ea": "0x14015f4d8",
    "module": "OLEAUT32",
    "name": "__imp_VariantChangeType",
    "ordinal": 12
  },
  {
    "ea": "0x14015f4b8",
    "module": "OLEAUT32",
    "name": "__imp_SafeArrayCreate",
    "ordinal": 15
  },
  {
    "ea": "0x14015f470",
    "module": "OLEAUT32",
    "name": "__imp_SafeArrayDestroy",
    "ordinal": 16
  },
  {
    "ea": "0x14015f460",
    "module": "OLEAUT32",
    "name": "__imp_SafeArrayGetUBound",
    "ordinal": 19
  },
  {
    "ea": "0x14015f458",
    "module": "OLEAUT32",
    "name": "__imp_SafeArrayGetLBound",
    "ordinal": 20
  },
  {
    "ea": "0x14015f4e0",
    "module": "OLEAUT32",
    "name": "__imp_SafeArrayLock",
    "ordinal": 21
  },
  {
    "ea": "0x14015f468",
    "module": "OLEAUT32",
    "name": "__imp_SafeArrayUnlock",
    "ordinal": 22
  },
  {
    "ea": "0x14015f480",
    "module": "OLEAUT32",
    "name": "__imp_SafeArrayGetVartype",
    "ordinal": 77
  },
  {
    "ea": "0x14015f478",
    "module": "OLEAUT32",
    "name": "__imp_SysStringByteLen",
    "ordinal": 149
  },
  {
    "ea": "0x14015f4a8",
    "module": "OLEAUT32",
    "name": "__imp_SysAllocStringByteLen",
    "ordinal": 150
  },
  {
    "ea": "0x14015f4e8",
    "module": "OLEAUT32",
    "name": "__imp_LoadTypeLib",
    "ordinal": 161
  },
  {
    "ea": "0x14015f4c8",
    "module": "OLEAUT32",
    "name": "__imp_RegisterTypeLib",
    "ordinal": 163
  },
  {
    "ea": "0x14015f4f8",
    "module": "OLEAUT32",
    "name": "__imp_UnRegisterTypeLib",
    "ordinal": 186
  },
  {
    "ea": "0x14015f4b0",
    "module": "OLEAUT32",
    "name": "__imp_VarUI4FromStr",
    "ordinal": 277
  },
  {
    "ea": "0x14015f550",
    "module": "SHELL32",
    "name": "SHGetPathFromIDListW",
    "ordinal": 0
  },
  {
    "ea": "0x14015f558",
    "module": "SHELL32",
    "name": "SHGetMalloc",
    "ordinal": 0
  },
  {
    "ea": "0x14015f560",
    "module": "SHELL32",
    "name": "CommandLineToArgvW",
    "ordinal": 0
  },
  {
    "ea": "0x14015f568",
    "module": "SHELL32",
    "name": "SHGetKnownFolderPath",
    "ordinal": 0
  },
  {
    "ea": "0x14015f570",
    "module": "SHELL32",
    "name": "SHGetFileInfoW",
    "ordinal": 0
  },
  {
    "ea": "0x14015f578",
    "module": "SHELL32",
    "name": "SHGetSpecialFolderLocation",
    "ordinal": 0
  },
  {
    "ea": "0x14015f580",
    "module": "SHELL32",
    "name": "SHGetDesktopFolder",
    "ordinal": 0
  },
  {
    "ea": "0x14015f588",
    "module": "SHELL32",
    "name": "SHAddToRecentDocs",
    "ordinal": 0
  },
  {
    "ea": "0x14015f590",
    "module": "SHELL32",
    "name": "ShellExecuteExW",
    "ordinal": 0
  },
  {
    "ea": "0x14015f1b0",
    "module": "COMCTL32",
    "name": "TaskDialogIndirect",
    "ordinal": 0
  },
  {
    "ea": "0x14015f1b8",
    "module": "COMCTL32",
    "name": "ImageList_Destroy",
    "ordinal": 0
  },
  {
    "ea": "0x14015f1c0",
    "module": "COMCTL32",
    "name": "ImageList_ReplaceIcon",
    "ordinal": 0
  },
  {
    "ea": "0x14015f1c8",
    "module": "COMCTL32",
    "name": "ImageList_Create",
    "ordinal": 0
  },
  {
    "ea": "0x14015f1d8",
    "module": "COMCTL32",
    "name": "InitCommonControlsEx",
    "ordinal": 0
  },
  {
    "ea": "0x14015f1e0",
    "module": "COMCTL32",
    "name": "ImageList_Add",
    "ordinal": 0
  },
  {
    "ea": "0x14015f1e8",
    "module": "COMCTL32",
    "name": "ImageList_GetImageCount",
    "ordinal": 0
  },
  {
    "ea": "0x14015f1a8",
    "module": "COMCTL32",
    "name": "__imp_InitCommonControls",
    "ordinal": 17
  },
  {
    "ea": "0x14015f1d0",
    "module": "COMCTL32",
    "name": "__imp_SetWindowSubclass",
    "ordinal": 410
  },
  {
    "ea": "0x14015f1f0",
    "module": "COMCTL32",
    "name": "__imp_RemoveWindowSubclass",
    "ordinal": 412
  },
  {
    "ea": "0x14015f1a0",
    "module": "COMCTL32",
    "name": "__imp_DefSubclassProc",
    "ordinal": 413
  },
  {
    "ea": "0x14015f200",
    "module": "COMDLG32",
    "name": "GetSaveFileNameW",
    "ordinal": 0
  },
  {
    "ea": "0x14015f208",
    "module": "COMDLG32",
    "name": "GetFileTitleW",
    "ordinal": 0
  },
  {
    "ea": "0x14015f210",
    "module": "COMDLG32",
    "name": "GetOpenFileNameW",
    "ordinal": 0
  },
  {
    "ea": "0x14015f220",
    "module": "CRYPT32",
    "name": "CryptStringToBinaryW",
    "ordinal": 0
  },
  {
    "ea": "0x14015f228",
    "module": "CRYPT32",
    "name": "CertDuplicateCertificateContext",
    "ordinal": 0
  },
  {
    "ea": "0x14015f230",
    "module": "CRYPT32",
    "name": "CryptUnprotectData",
    "ordinal": 0
  },
  {
    "ea": "0x14015f238",
    "module": "CRYPT32",
    "name": "CertGetCertificateContextProperty",
    "ordinal": 0
  },
  {
    "ea": "0x14015f240",
    "module": "CRYPT32",
    "name": "CryptSignMessage",
    "ordinal": 0
  },
  {
    "ea": "0x14015f248",
    "module": "CRYPT32",
    "name": "CryptVerifyDetachedMessageSignature",
    "ordinal": 0
  },
  {
    "ea": "0x14015f250",
    "module": "CRYPT32",
    "name": "CryptMsgClose",
    "ordinal": 0
  },
  {
    "ea": "0x14015f258",
    "module": "CRYPT32",
    "name": "CryptProtectData",
    "ordinal": 0
  },
  {
    "ea": "0x14015f260",
    "module": "CRYPT32",
    "name": "CryptBinaryToStringW",
    "ordinal": 0
  },
  {
    "ea": "0x14015f268",
    "module": "CRYPT32",
    "name": "CertDuplicateCertificateChain",
    "ordinal": 0
  },
  {
    "ea": "0x14015f270",
    "module": "CRYPT32",
    "name": "CertFreeCertificateContext",
    "ordinal": 0
  },
  {
    "ea": "0x14015f278",
    "module": "CRYPT32",
    "name": "CertFreeCertificateChain",
    "ordinal": 0
  },
  {
    "ea": "0x14015f280",
    "module": "CRYPT32",
    "name": "CertGetCertificateChain",
    "ordinal": 0
  },
  {
    "ea": "0x14015f288",
    "module": "CRYPT32",
    "name": "CertGetEnhancedKeyUsage",
    "ordinal": 0
  },
  {
    "ea": "0x14015f290",
    "module": "CRYPT32",
    "name": "CryptDecodeObject",
    "ordinal": 0
  },
  {
    "ea": "0x14015f298",
    "module": "CRYPT32",
    "name": "CertCloseStore",
    "ordinal": 0
  },
  {
    "ea": "0x14015f2a0",
    "module": "CRYPT32",
    "name": "CertVerifyCertificateChainPolicy",
    "ordinal": 0
  },
  {
    "ea": "0x14015f2a8",
    "module": "CRYPT32",
    "name": "CryptMsgOpenToDecode",
    "ordinal": 0
  },
  {
    "ea": "0x14015f2b0",
    "module": "CRYPT32",
    "name": "CryptMsgUpdate",
    "ordinal": 0
  },
  {
    "ea": "0x14015f2b8",
    "module": "CRYPT32",
    "name": "CertFindExtension",
    "ordinal": 0
  },
  {
    "ea": "0x14015f2c0",
    "module": "CRYPT32",
    "name": "CertOpenStore",
    "ordinal": 0
  },
  {
    "ea": "0x14015f5d8",
    "module": "WINHTTP",
    "name": "WinHttpQueryOption",
    "ordinal": 0
  },
  {
    "ea": "0x14015f5e0",
    "module": "WINHTTP",
    "name": "WinHttpOpen",
    "ordinal": 0
  },
  {
    "ea": "0x14015f5e8",
    "module": "WINHTTP",
    "name": "WinHttpConnect",
    "ordinal": 0
  },
  {
    "ea": "0x14015f5f0",
    "module": "WINHTTP",
    "name": "WinHttpOpenRequest",
    "ordinal": 0
  },
  {
    "ea": "0x14015f5f8",
    "module": "WINHTTP",
    "name": "WinHttpSendRequest",
    "ordinal": 0
  },
  {
    "ea": "0x14015f600",
    "module": "WINHTTP",
    "name": "WinHttpCloseHandle",
    "ordinal": 0
  },
  {
    "ea": "0x14015f508",
    "module": "RPCRT4",
    "name": "RpcBindingFromStringBindingW",
    "ordinal": 0
  },
  {
    "ea": "0x14015f510",
    "module": "RPCRT4",
    "name": "RpcBindingFree",
    "ordinal": 0
  },
  {
    "ea": "0x14015f518",
    "module": "RPCRT4",
    "name": "I_RpcExceptionFilter",
    "ordinal": 0
  },
  {
    "ea": "0x14015f520",
    "module": "RPCRT4",
    "name": "NdrClientCall3",
    "ordinal": 0
  },
  {
    "ea": "0x14015f528",
    "module": "RPCRT4",
    "name": "UuidFromStringW",
    "ordinal": 0
  },
  {
    "ea": "0x14015f530",
    "module": "RPCRT4",
    "name": "RpcBindingSetAuthInfoExW",
    "ordinal": 0
  },
  {
    "ea": "0x14015f538",
    "module": "RPCRT4",
    "name": "RpcStringBindingComposeW",
    "ordinal": 0
  },
  {
    "ea": "0x14015f540",
    "module": "RPCRT4",
    "name": "RpcStringFreeW",
    "ordinal": 0
  },
  {
    "ea": "0x14015f778",
    "module": "credui",
    "name": "CredUIPromptForWindowsCredentialsW",
    "ordinal": 0
  },
  {
    "ea": "0x14015f780",
    "module": "credui",
    "name": "CredUnPackAuthenticationBufferW",
    "ordinal": 0
  },
  {
    "ea": "0x14015f788",
    "module": "credui",
    "name": "CredPackAuthenticationBufferW",
    "ordinal": 0
  },
  {
    "ea": "0x14015f790",
    "module": "credui",
    "name": "CredUIParseUserNameW",
    "ordinal": 0
  },
  {
    "ea": "0x14015f5a0",
    "module": "Secur32",
    "name": "GetUserNameExW",
    "ordinal": 0
  },
  {
    "ea": "0x14015f5a8",
    "module": "Secur32",
    "name": "LsaDeregisterLogonProcess",
    "ordinal": 0
  },
  {
    "ea": "0x14015f5b0",
    "module": "Secur32",
    "name": "LsaConnectUntrusted",
    "ordinal": 0
  },
  {
    "ea": "0x14015f5b8",
    "module": "Secur32",
    "name": "FreeContextBuffer",
    "ordinal": 0
  },
  {
    "ea": "0x14015f5c0",
    "module": "Secur32",
    "name": "QuerySecurityPackageInfoW",
    "ordinal": 0
  },
  {
    "ea": "0x14015f5c8",
    "module": "Secur32",
    "name": "LsaLookupAuthenticationPackage",
    "ordinal": 0
  },
  {
    "ea": "0x14015f7a0",
    "module": "cryptui",
    "name": "CryptUIDlgViewCertificateW",
    "ordinal": 0
  },
  {
    "ea": "0x14015f178",
    "module": "CFGMGR32",
    "name": "CM_Get_Parent",
    "ordinal": 0
  },
  {
    "ea": "0x14015f180",
    "module": "CFGMGR32",
    "name": "CM_Get_Child",
    "ordinal": 0
  },
  {
    "ea": "0x14015f188",
    "module": "CFGMGR32",
    "name": "CM_Get_DevNode_Registry_PropertyW",
    "ordinal": 0
  },
  {
    "ea": "0x14015f190",
    "module": "CFGMGR32",
    "name": "CM_Get_Sibling",
    "ordinal": 0
  },
  {
    "ea": "0x14015f418",
    "module": "IPHLPAPI",
    "name": "CreateSortedAddressPairs",
    "ordinal": 0
  },
  {
    "ea": "0x14015f420",
    "module": "IPHLPAPI",
    "name": "GetAdaptersAddresses",
    "ordinal": 0
  },
  {
    "ea": "0x14015f428",
    "module": "IPHLPAPI",
    "name": "FreeMibTable",
    "ordinal": 0
  },
  {
    "ea": "0x14015f430",
    "module": "IPHLPAPI",
    "name": "ParseNetworkString",
    "ordinal": 0
  },
  {
    "ea": "0x14015f710",
    "module": "api-ms-win-core-winrt-l1-1-0",
    "name": "RoGetActivationFactory",
    "ordinal": 0
  },
  {
    "ea": "0x14015f718",
    "module": "api-ms-win-core-winrt-l1-1-0",
    "name": "RoActivateInstance",
    "ordinal": 0
  },
  {
    "ea": "0x14015f720",
    "module": "api-ms-win-core-winrt-l1-1-0",
    "name": "RoUninitialize",
    "ordinal": 0
  },
  {
    "ea": "0x14015f728",
    "module": "api-ms-win-core-winrt-l1-1-0",
    "name": "RoInitialize",
    "ordinal": 0
  },
  {
    "ea": "0x14015f738",
    "module": "api-ms-win-core-winrt-string-l1-1-0",
    "name": "WindowsCreateStringReference",
    "ordinal": 0
  },
  {
    "ea": "0x14015f740",
    "module": "api-ms-win-core-winrt-string-l1-1-0",
    "name": "WindowsDeleteString",
    "ordinal": 0
  },
  {
    "ea": "0x14015f000",
    "module": "ADVAPI32",
    "name": "GetAce",
    "ordinal": 0
  },
  {
    "ea": "0x14015f008",
    "module": "ADVAPI32",
    "name": "GetSecurityInfo",
    "ordinal": 0
  },
  {
    "ea": "0x14015f010",
    "module": "ADVAPI32",
    "name": "OpenProcessToken",
    "ordinal": 0
  },
  {
    "ea": "0x14015f018",
    "module": "ADVAPI32",
    "name": "OpenThreadToken",
    "ordinal": 0
  },
  {
    "ea": "0x14015f020",
    "module": "ADVAPI32",
    "name": "UnregisterTraceGuids",
    "ordinal": 0
  },
  {
    "ea": "0x14015f028",
    "module": "ADVAPI32",
    "name": "RegisterTraceGuidsW",
    "ordinal": 0
  },
  {
    "ea": "0x14015f030",
    "module": "ADVAPI32",
    "name": "GetTraceEnableFlags",
    "ordinal": 0
  },
  {
    "ea": "0x14015f038",
    "module": "ADVAPI32",
    "name": "GetTraceEnableLevel",
    "ordinal": 0
  },
  {
    "ea": "0x14015f040",
    "module": "ADVAPI32",
    "name": "GetTraceLoggerHandle",
    "ordinal": 0
  },
  {
    "ea": "0x14015f048",
    "module": "ADVAPI32",
    "name": "EventWriteTransfer",
    "ordinal": 0
  },
  {
    "ea": "0x14015f050",
    "module": "ADVAPI32",
    "name": "EventSetInformation",
    "ordinal": 0
  },
  {
    "ea": "0x14015f058",
    "module": "ADVAPI32",
    "name": "EventRegister",
    "ordinal": 0
  },
  {
    "ea": "0x14015f060",
    "module": "ADVAPI32",
    "name": "EventUnregister",
    "ordinal": 0
  },
  {
    "ea": "0x14015f068",
    "module": "ADVAPI32",
    "name": "TraceMessage",
    "ordinal": 0
  },
  {
    "ea": "0x14015f070",
    "module": "ADVAPI32",
    "name": "RegDeleteValueW",
    "ordinal": 0
  },
  {
    "ea": "0x14015f078",
    "module": "ADVAPI32",
    "name": "RegCreateKeyExW",
    "ordinal": 0
  },
  {
    "ea": "0x14015f080",
    "module": "ADVAPI32",
    "name": "RegSetValueExW",
    "ordinal": 0
  },
  {
    "ea": "0x14015f088",
    "module": "ADVAPI32",
    "name": "RegOpenKeyExW",
    "ordinal": 0
  },
  {
    "ea": "0x14015f090",
    "module": "ADVAPI32",
    "name": "RegEnumKeyExW",
    "ordinal": 0
  },
  {
    "ea": "0x14015f098",
    "module": "ADVAPI32",
    "name": "RegQueryInfoKeyW",
    "ordinal": 0
  },
  {
    "ea": "0x14015f0a0",
    "module": "ADVAPI32",
    "name": "RegCloseKey",
    "ordinal": 0
  },
  {
    "ea": "0x14015f0a8",
    "module": "ADVAPI32",
    "name": "GetSidSubAuthorityCount",
    "ordinal": 0
  },
  {
    "ea": "0x14015f0b0",
    "module": "ADVAPI32",
    "name": "GetSidSubAuthority",
    "ordinal": 0
  },
  {
    "ea": "0x14015f0b8",
    "module": "ADVAPI32",
    "name": "LookupPrivilegeValueW",
    "ordinal": 0
  },
  {
    "ea": "0x14015f0c0",
    "module": "ADVAPI32",
    "name": "AdjustTokenPrivileges",
    "ordinal": 0
  },
  {
    "ea": "0x14015f0c8",
    "module": "ADVAPI32",
    "name": "InitiateSystemShutdownExW",
    "ordinal": 0
  },
  {
    "ea": "0x14015f0d0",
    "module": "ADVAPI32",
    "name": "EventActivityIdControl",
    "ordinal": 0
  },
  {
    "ea": "0x14015f0d8",
    "module": "ADVAPI32",
    "name": "RegQueryValueExW",
    "ordinal": 0
  },
  {
    "ea": "0x14015f0e0",
    "module": "ADVAPI32",
    "name": "CryptAcquireContextW",
    "ordinal": 0
  },
  {
    "ea": "0x14015f0e8",
    "module": "ADVAPI32",
    "name": "CryptGenRandom",
    "ordinal": 0
  },
  {
    "ea": "0x14015f0f0",
    "module": "ADVAPI32",
    "name": "CryptReleaseContext",
    "ordinal": 0
  },
  {
    "ea": "0x14015f0f8",
    "module": "ADVAPI32",
    "name": "RegGetValueW",
    "ordinal": 0
  },
  {
    "ea": "0x14015f100",
    "module": "ADVAPI32",
    "name": "CredDeleteW",
    "ordinal": 0
  },
  {
    "ea": "0x14015f108",
    "module": "ADVAPI32",
    "name": "CredFree",
    "ordinal": 0
  },
  {
    "ea": "0x14015f110",
    "module": "ADVAPI32",
    "name": "CredReadDomainCredentialsW",
    "ordinal": 0
  },
  {
    "ea": "0x14015f118",
    "module": "ADVAPI32",
    "name": "CredWriteDomainCredentialsW",
    "ordinal": 0
  },
  {
    "ea": "0x14015f120",
    "module": "ADVAPI32",
    "name": "CredIsMarshaledCredentialW",
    "ordinal": 0
  },
  {
    "ea": "0x14015f128",
    "module": "ADVAPI32",
    "name": "CredUnmarshalCredentialW",
    "ordinal": 0
  },
  {
    "ea": "0x14015f130",
    "module": "ADVAPI32",
    "name": "RegEnumValueW",
    "ordinal": 0
  },
  {
    "ea": "0x14015f138",
    "module": "ADVAPI32",
    "name": "RegDeleteTreeW",
    "ordinal": 0
  },
  {
    "ea": "0x14015f140",
    "module": "ADVAPI32",
    "name": "IsTextUnicode",
    "ordinal": 0
  },
  {
    "ea": "0x14015f148",
    "module": "ADVAPI32",
    "name": "CredReadW",
    "ordinal": 0
  },
  {
    "ea": "0x14015f150",
    "module": "ADVAPI32",
    "name": "CredWriteW",
    "ordinal": 0
  },
  {
    "ea": "0x14015f158",
    "module": "ADVAPI32",
    "name": "CredGetSessionTypes",
    "ordinal": 0
  },
  {
    "ea": "0x14015f160",
    "module": "ADVAPI32",
    "name": "CreateWellKnownSid",
    "ordinal": 0
  },
  {
    "ea": "0x14015f168",
    "module": "ADVAPI32",
    "name": "GetAclInformation",
    "ordinal": 0
  },
  {
    "ea": "0x14015f2d0",
    "module": "DismApi",
    "name": "DismOpenSession",
    "ordinal": 0
  },
  {
    "ea": "0x14015f2d8",
    "module": "DismApi",
    "name": "DismInitialize",
    "ordinal": 0
  },
  {
    "ea": "0x14015f2e0",
    "module": "DismApi",
    "name": "DismDisableFeature",
    "ordinal": 0
  },
  {
    "ea": "0x14015f2e8",
    "module": "DismApi",
    "name": "DismCloseSession",
    "ordinal": 0
  },
  {
    "ea": "0x14015f2f0",
    "module": "DismApi",
    "name": "DismShutdown",
    "ordinal": 0
  },
  {
    "ea": "0x14015f2f8",
    "module": "DismApi",
    "name": "DismGetFeatureInfo",
    "ordinal": 0
  },
  {
    "ea": "0x14015f300",
    "module": "DismApi",
    "name": "DismDelete",
    "ordinal": 0
  },
  {
    "ea": "0x14015f628",
    "module": "WS2_32",
    "name": "WSARecv",
    "ordinal": 0
  },
  {
    "ea": "0x14015f638",
    "module": "WS2_32",
    "name": "GetNameInfoW",
    "ordinal": 0
  },
  {
    "ea": "0x14015f650",
    "module": "WS2_32",
    "name": "GetAddrInfoExW",
    "ordinal": 0
  },
  {
    "ea": "0x14015f698",
    "module": "WS2_32",
    "name": "WSAEventSelect",
    "ordinal": 0
  },
  {
    "ea": "0x14015f6a8",
    "module": "WS2_32",
    "name": "WSAStringToAddressW",
    "ordinal": 0
  },
  {
    "ea": "0x14015f6c0",
    "module": "WS2_32",
    "name": "WSAIoctl",
    "ordinal": 0
  },
  {
    "ea": "0x14015f6c8",
    "module": "WS2_32",
    "name": "GetAddrInfoW",
    "ordinal": 0
  },
  {
    "ea": "0x14015f6d0",
    "module": "WS2_32",
    "name": "FreeAddrInfoW",
    "ordinal": 0
  },
  {
    "ea": "0x14015f6d8",
    "module": "WS2_32",
    "name": "WSAAddressToStringW",
    "ordinal": 0
  },
  {
    "ea": "0x14015f6e8",
    "module": "WS2_32",
    "name": "FreeAddrInfoExW",
    "ordinal": 0
  },
  {
    "ea": "0x14015f6f8",
    "module": "WS2_32",
    "name": "WSASocketW",
    "ordinal": 0
  },
  {
    "ea": "0x14015f700",
    "module": "WS2_32",
    "name": "WSASend",
    "ordinal": 0
  },
  {
    "ea": "0x14015f6f0",
    "module": "WS2_32",
    "name": "__imp_accept",
    "ordinal": 1
  },
  {
    "ea": "0x14015f658",
    "module": "WS2_32",
    "name": "__imp_bind",
    "ordinal": 2
  },
  {
    "ea": "0x14015f680",
    "module": "WS2_32",
    "name": "__imp_closesocket",
    "ordinal": 3
  },
  {
    "ea": "0x14015f668",
    "module": "WS2_32",
    "name": "__imp_connect",
    "ordinal": 4
  },
  {
    "ea": "0x14015f6e0",
    "module": "WS2_32",
    "name": "__imp_getpeername",
    "ordinal": 5
  },
  {
    "ea": "0x14015f648",
    "module": "WS2_32",
    "name": "__imp_getsockname",
    "ordinal": 6
  },
  {
    "ea": "0x14015f690",
    "module": "WS2_32",
    "name": "__imp_getsockopt",
    "ordinal": 7
  },
  {
    "ea": "0x14015f660",
    "module": "WS2_32",
    "name": "__imp_htons",
    "ordinal": 9
  },
  {
    "ea": "0x14015f630",
    "module": "WS2_32",
    "name": "__imp_listen",
    "ordinal": 13
  },
  {
    "ea": "0x14015f640",
    "module": "WS2_32",
    "name": "__imp_ntohs",
    "ordinal": 15
  },
  {
    "ea": "0x14015f6b0",
    "module": "WS2_32",
    "name": "__imp_recv",
    "ordinal": 16
  },
  {
    "ea": "0x14015f6b8",
    "module": "WS2_32",
    "name": "__imp_select",
    "ordinal": 18
  },
  {
    "ea": "0x14015f6a0",
    "module": "WS2_32",
    "name": "__imp_send",
    "ordinal": 19
  },
  {
    "ea": "0x14015f670",
    "module": "WS2_32",
    "name": "__imp_setsockopt",
    "ordinal": 21
  },
  {
    "ea": "0x14015f620",
    "module": "WS2_32",
    "name": "__imp_shutdown",
    "ordinal": 22
  },
  {
    "ea": "0x14015f678",
    "module": "WS2_32",
    "name": "__imp_socket",
    "ordinal": 23
  },
  {
    "ea": "0x14015f688",
    "module": "WS2_32",
    "name": "__imp_WSAGetLastError",
    "ordinal": 111
  },
  {
    "ea": "0x14015f610",
    "module": "WS2_32",
    "name": "__imp_WSAStartup",
    "ordinal": 115
  },
  {
    "ea": "0x14015f618",
    "module": "WS2_32",
    "name": "__imp_WSACleanup",
    "ordinal": 116
  },
  {
    "ea": "0x14015f440",
    "module": "NETAPI32",
    "name": "NetGetJoinInformation",
    "ordinal": 0
  },
  {
    "ea": "0x14015f448",
    "module": "NETAPI32",
    "name": "NetApiBufferFree",
    "ordinal": 0
  },
  {
    "ea": "0x14015f750",
    "module": "api-ms-win-mm-misc-l2-1-0",
    "name": "timeKillEvent",
    "ordinal": 0
  },
  {
    "ea": "0x14015f758",
    "module": "api-ms-win-mm-misc-l2-1-0",
    "name": "timeSetEvent",
    "ordinal": 0
  },
  {
    "ea": "0x14015f768",
    "module": "api-ms-win-mm-time-l1-1-0",
    "name": "timeGetTime",
    "ordinal": 0
  }
]