{
  "counts": {
    "export_count": 1,
    "function_count": 118,
    "import_count": 113,
    "import_xref_count": 895,
    "max_decompile": 250,
    "max_disasm_funcs": 250,
    "name_count": 401,
    "risk_function_count": 84,
    "segment_count": 9,
    "string_count": 169
  },
  "databasePath": "filecrypt_run_280075fe.i64",
  "idb_path": "filecrypt_run_280075fe.i64",
  "imagebase": "0x140000000",
  "input_file": "filecrypt.sys",
  "is_64bit": true,
  "md5": "8c052784ba75d10feedcaf5c553a1642",
  "modules": {},
  "name": "filecrypt_run_280075fe",
  "processor": "metapc",
  "sha256": "1030a656c8b4030d6ae5343fbf47cf88ca4b62bb2f56aafd59664e1ccaac5490",
  "source_basename": "filecrypt_run_280075fe.i64",
  "source_id": "133a53a52f6e"
}